<?xml version='1.0' encoding='UTF-8'?>
<!DOCTYPE hibernate-configuration PUBLIC
          "-//Hibernate/Hibernate Configuration DTD 3.0//EN"
          "http://www.hibernate.org/dtd/hibernate-configuration-3.0.dtd">
<!-- Generated by MyEclipse Hibernate Tools.                   -->
<hibernate-configuration>

	<session-factory>
		<property name="myeclipse.connection.profile">
			ssh_test
		</property>
		<property name="dialect">
			org.hibernate.dialect.MySQL5Dialect
		</property>
		<property name="hibernate.current_session_context_class">thread</property>
		<property name="show_sql">true</property>
		<property name="format_sql">true</property>
		<property name="hbm2ddl.auto">update</property>
		<mapping resource="org/sinmem/bean/Institute.hbm.xml" />
		<mapping resource="org/sinmem/bean/Major.hbm.xml" />
		<mapping resource="org/sinmem/bean/Teacher.hbm.xml" />
		<mapping resource="org/sinmem/bean/Experimentclause.hbm.xml" />
		<mapping resource="org/sinmem/bean/Course.hbm.xml" />
		<mapping resource="org/sinmem/bean/Clazz.hbm.xml" />
		<mapping resource="org/sinmem/bean/Experimentscores.hbm.xml" />
		<mapping resource="org/sinmem/bean/Courseclass.hbm.xml" />
		<mapping resource="org/sinmem/bean/Student.hbm.xml" />
		<mapping resource="org/sinmem/bean/Admin.hbm.xml" />
		<mapping resource="org/sinmem/bean/SC.hbm.xml" />
		<mapping resource="org/sinmem/bean/Cexperiment.hbm.xml" />
		<mapping resource="org/sinmem/bean/Experimentclauses.hbm.xml" />
		<mapping resource="org/sinmem/bean/Cexperiments.hbm.xml" />

	</session-factory>

</hibernate-configuration>