<?xml version="1.0" encoding="utf-8"?>
<!DOCTYPE hibernate-mapping PUBLIC "-//Hibernate/Hibernate Mapping DTD 3.0//EN"
"http://www.hibernate.org/dtd/hibernate-mapping-3.0.dtd">
<!-- 
    Mapping file autogenerated by MyEclipse Persistence Tools
-->
<hibernate-mapping>
    <class name="org.sinmem.bean.Courseclass" table="courseclass" catalog="ssh_test">
        <composite-id name="id" class="org.sinmem.bean.CourseclassId">
            <key-many-to-one name="course" class="org.sinmem.bean.Course">
                <column name="courseNo" length="8" />
            </key-many-to-one>
            <key-property name="cclassNo" type="java.lang.String">
                <column name="cClassNo" length="19" />
            </key-property>
        </composite-id>
        <many-to-one name="teacher" class="org.sinmem.bean.Teacher" fetch="select">
            <column name="teacherNo" length="6" not-null="true" />
        </many-to-one>
        <property name="number" type="java.lang.Integer">
            <column name="number" not-null="true" />
        </property>
        <property name="count" type="java.lang.Integer">
            <column name="count" not-null="true" />
        </property>
        <property name="term" type="java.lang.Integer">
            <column name="term" not-null="true" />
        </property>
        <property name="time" type="java.lang.Integer">
            <column name="time" not-null="true" />
        </property>
        <set name="SCs" inverse="true">
            <key>
                <column name="courseNo" length="8" not-null="true" />
                <column name="cClassNo" length="19" not-null="true" />
            </key>
            <one-to-many class="org.sinmem.bean.SC" />
        </set>
    </class>
</hibernate-mapping>
